{
	"BatchList": [
		{
			"BatchID": 1,
			"BatchName": "Batch 001",
			"AccountNumber": 46733,
			"DocCount": 20,
			"Datetime": "12/10/2023",
			"Status": "Processed"
		},
		{
			"BatchID": 2,
			"BatchName": "Batch 002",
			"AccountNumber": 46733,
			"DocCount": 20,
			"Datetime": "12/10/2023",
			"Status": "Processed"
		},
		{
			"BatchID": 3,
			"BatchName": "Batch 003",
			"AccountNumber": 46734,
			"DocCount": 22,
			"Datetime": "12/10/2023",
			"Status": "Pending"
		}
	],
	"DocList": [
		{
			"DocID": 1,
			"DocName": "DocID 00123",
			"DocType": "PDF",
			"DateCreated": "20/10/2023  23:12:11",
			"DocSize": 23,
			"Amount": 12943.23,
			"AccountNumber": 67343,
			"Unread": "Yes"
		},
		{
			"DocID": 2,
			"DocName": "DocID 99234",
			"DocType": "PDF",
			"DateCreated": "15/10/2022  10:15:22",
			"DocSize": 34,
			"Amount": 165.55,
			"AccountNumber": 67343,
			"Unread": "Yes"
		},
		{
			"DocID": 3,
			"DocName": "DocID 33232",
			"DocType": "PDF",
			"DateCreated": "12/10/2023  09:33:00",
			"DocSize": 22,
			"Amount": 456.12,
			"AccountNumber": 67344,
			"Unread": "No"
		},
		{
			"DocID": 4,
			"DocName": "DocID 23422",
			"DocType": "PDF",
			"DateCreated": "24/02/2022  10:12:22",
			"DocSize": 120,
			"Amount": 4568.4,
			"AccountNumber": 67344,
			"Unread": "No"
		}
	],
	"AccountList": [
		{
			"AccountID": 1,
			"AccountName": "Account 1",
			"SignupDate": "10/12/2022",
			"AccountNumber": 67343,
			"Status": "Active",
			"AccountManager": "Triv Singh"
		},
		{
			"AccountID": 2,
			"AccountName": "Account 2",
			"SignupDate": "15/12/2022",
			"AccountNumber": 67344,
			"Status": "Dormant",
			"AccountManager": "James Hunt"
		}
	],
	"AccountDetails": [
		{
			"AccountID": 1,
			"AccountNumber": 67343,
			"PrimaryRecipient": "Jsmith",
			"PrimaryRecipientEmail": "james.Smith@test.com",
			"InvoicePrint": 1,
			"InvoiceEmail": 0,
			"InvoicePush": 0,
			"InvoicePushSingle": 0,
			"InvoicePushMerge": 0,
			"InvoiceDiscard": 0,
			"CreditPrint": 0,
			"CreditEmail": 1,
			"CreditPush": 1,
			"CreditPushSingle": 0,
			"CreditPushMerge": 0,
			"CreditDiscard": 0
		},
		{
			"AccountID": 2,
			"AccountNumber": 67344,
			"PrimaryRecipient": "JSmith2",
			"PrimaryRecipientEmail": "james.Smith@test123.com",
			"InvoicePrint": 0,
			"InvoiceEmail": 0,
			"InvoicePush": 1,
			"InvoicePushSingle": 0,
			"InvoicePushMerge": 0,
			"InvoiceDiscard": 0,
			"CreditPrint": 0,
			"CreditEmail": 0,
			"CreditPush": 0,
			"CreditPushSingle": 1,
			"CreditPushMerge": 0,
			"CreditDiscard": 0
		}
	],
	"UserList": [
		{
			"UserID": 1,
			"UserName": "Jsmith",
			"Email": "james.Smith@test.com",
			"FirstName": "James",
			"LastName": "Smith",
			"UserRole": "User",
			"Accounts": [
				"a",
				"b",
				"c"
			]
		},
		{
			"UserID": 2,
			"UserName": "Jdoe",
			"Email": "Jane.Doe@test.com",
			"FirstName": "Jane",
			"LastName": "Doe",
			"UserRole": "User",
			"Accounts": [
				"a",
				"b",
				"c"
			]
		},
		{
			"UserID": 3,
			"UserName": "Jsmith",
			"Email": "james.Smith@test123.com",
			"FirstName": "James",
			"LastName": "Smith",
			"UserRole": "User",
			"Accounts": [
				"a",
				"b",
				"c"
			]
		},
		{
			"UserID": 4,
			"UserName": "Jdoe",
			"Email": "Jane.Doe@test123.com",
			"FirstName": "Jane",
			"LastName": "Doe",
			"UserRole": "User",
			"Accounts": [
				"a",
				"b",
				"c"
			]
		}
	]
}
